my_flask_api/__init__.py
my_flask_api/app.py
my_flask_api-0.1.dist-info/METADATA
my_flask_api-0.1.dist-info/WHEEL
my_flask_api-0.1.dist-info/entry_points.txt
my_flask_api-0.1.dist-info/top_level.txt
my_flask_api-0.1.dist-info/RECORD
